twine_verify_upload/__init__.py
twine_verify_upload/command.py
twine_verify_upload-0.0.3.dist-info/LICENSE
twine_verify_upload-0.0.3.dist-info/METADATA
twine_verify_upload-0.0.3.dist-info/WHEEL
twine_verify_upload-0.0.3.dist-info/entry_points.txt
twine_verify_upload-0.0.3.dist-info/top_level.txt
twine_verify_upload-0.0.3.dist-info/RECORD
