Metadata-Version: 2.1
Name: twine-verify-upload
Version: 0.0.3
Summary: Adds "verify-upload" command to twine.
Home-page: UNKNOWN
Author: Blazej Michalik
Author-email: im.mr.mino@gmail.com
License: UNKNOWN
Project-URL: Source, https://github.com/MrMino/twine-verify-upload
Platform: UNKNOWN
Classifier: Intended Audience :: Developers
Classifier: License :: OSI Approved :: Apache Software License
Classifier: Natural Language :: English
Classifier: Operating System :: MacOS :: MacOS X
Classifier: Operating System :: POSIX
Classifier: Operating System :: POSIX :: BSD
Classifier: Operating System :: POSIX :: Linux
Classifier: Operating System :: Microsoft :: Windows
Classifier: Programming Language :: Python
Classifier: Programming Language :: Python :: 3
Classifier: Programming Language :: Python :: 3 :: Only
Classifier: Programming Language :: Python :: 3.6
Classifier: Programming Language :: Python :: 3.7
Classifier: Programming Language :: Python :: 3.8
Classifier: Programming Language :: Python :: Implementation :: CPython
Requires-Python: >=3.6
Requires-Dist: pypi-simple (==0.6)
Requires-Dist: packaging
Requires-Dist: colorama
